pieces_copilot_sdk/__init__.py
pieces_copilot_sdk/client.py
pieces_copilot_sdk-0.5.0.dist-info/METADATA
pieces_copilot_sdk-0.5.0.dist-info/WHEEL
pieces_copilot_sdk-0.5.0.dist-info/RECORD
