Metadata-Version: 2.1
Name: pieces_copilot_sdk
Version: 0.5.0
Summary: A Pieces OS SDK wrapper that allows anyone to easily create a Pieces Copilot experience with minimal code.
License: MIT
Author: Mason Williams
Author-email: mason@pieces.app
Requires-Python: >=3.7,<4.0
Classifier: License :: OSI Approved :: MIT License
Classifier: Programming Language :: Python :: 3
Classifier: Programming Language :: Python :: 3.7
Classifier: Programming Language :: Python :: 3.8
Classifier: Programming Language :: Python :: 3.9
Classifier: Programming Language :: Python :: 3.10
Classifier: Programming Language :: Python :: 3.11
Classifier: Programming Language :: Python :: 3.12
Requires-Dist: pieces_os_client (>=2.6.0,<3.0.0)
